cdktf_cdktf_provider_kubernetes/__init__.py
cdktf_cdktf_provider_kubernetes/py.typed
cdktf_cdktf_provider_kubernetes/_jsii/__init__.py
cdktf_cdktf_provider_kubernetes/_jsii/provider-kubernetes@12.0.0.jsii.tgz
cdktf_cdktf_provider_kubernetes/annotations/__init__.py
cdktf_cdktf_provider_kubernetes/api_service/__init__.py
cdktf_cdktf_provider_kubernetes/api_service_v1/__init__.py
cdktf_cdktf_provider_kubernetes/certificate_signing_request/__init__.py
cdktf_cdktf_provider_kubernetes/certificate_signing_request_v1/__init__.py
cdktf_cdktf_provider_kubernetes/cluster_role/__init__.py
cdktf_cdktf_provider_kubernetes/cluster_role_binding/__init__.py
cdktf_cdktf_provider_kubernetes/cluster_role_binding_v1/__init__.py
cdktf_cdktf_provider_kubernetes/cluster_role_v1/__init__.py
cdktf_cdktf_provider_kubernetes/config_map/__init__.py
cdktf_cdktf_provider_kubernetes/config_map_v1/__init__.py
cdktf_cdktf_provider_kubernetes/config_map_v1_data/__init__.py
cdktf_cdktf_provider_kubernetes/cron_job/__init__.py
cdktf_cdktf_provider_kubernetes/cron_job_v1/__init__.py
cdktf_cdktf_provider_kubernetes/csi_driver/__init__.py
cdktf_cdktf_provider_kubernetes/csi_driver_v1/__init__.py
cdktf_cdktf_provider_kubernetes/daemon_set_v1/__init__.py
cdktf_cdktf_provider_kubernetes/daemonset/__init__.py
cdktf_cdktf_provider_kubernetes/data_kubernetes_all_namespaces/__init__.py
cdktf_cdktf_provider_kubernetes/data_kubernetes_config_map/__init__.py
cdktf_cdktf_provider_kubernetes/data_kubernetes_config_map_v1/__init__.py
cdktf_cdktf_provider_kubernetes/data_kubernetes_endpoints_v1/__init__.py
cdktf_cdktf_provider_kubernetes/data_kubernetes_ingress/__init__.py
cdktf_cdktf_provider_kubernetes/data_kubernetes_ingress_v1/__init__.py
cdktf_cdktf_provider_kubernetes/data_kubernetes_mutating_webhook_configuration_v1/__init__.py
cdktf_cdktf_provider_kubernetes/data_kubernetes_namespace/__init__.py
cdktf_cdktf_provider_kubernetes/data_kubernetes_namespace_v1/__init__.py
cdktf_cdktf_provider_kubernetes-12.0.0.dist-info/LICENSE
cdktf_cdktf_provider_kubernetes-12.0.0.dist-info/METADATA
cdktf_cdktf_provider_kubernetes-12.0.0.dist-info/WHEEL
cdktf_cdktf_provider_kubernetes-12.0.0.dist-info/top_level.txt
cdktf_cdktf_provider_kubernetes-12.0.0.dist-info/RECORD
